wzony/__init__.py
wzony/core.py
wzony/main.py
wzony/HBulider/NavigationBar.py
wzony/HBulider/__init__.py
wzony/HBulider/core.py
wzony/HNodes/DoubleMarker.py
wzony/HNodes/SelfDefine.py
wzony/HNodes/SingleMarker.py
wzony/HNodes/__init__.py
wzony-0.2.0.dist-info/licenses/LICENSE
wzony-0.2.0.dist-info/METADATA
wzony-0.2.0.dist-info/WHEEL
wzony-0.2.0.dist-info/top_level.txt
wzony-0.2.0.dist-info/RECORD
