Metadata-Version: 2.4
Name: wZony
Version: 0.2.0
Summary: Quickly Build WebUI with Python.
Author: Zonglin Guo
License: Apache
Project-URL: Source, https://github.com/kwokzl/wZony
Project-URL: Tracker, https://github.com/kwokzl/wZony/issues
Classifier: Topic :: Internet :: WWW/HTTP
Classifier: Topic :: Text Processing :: Markup :: HTML
Classifier: Programming Language :: Python :: 3
Requires-Python: >=3.6
License-File: LICENSE
Dynamic: author
Dynamic: classifier
Dynamic: description
Dynamic: description-content-type
Dynamic: license
Dynamic: license-file
Dynamic: project-url
Dynamic: requires-python
Dynamic: summary
